airworkflowdemo/__init__.py
airworkflowdemo/constants.py
airworkflowdemo/function_deployer.py
airworkflowdemo/master_config.py
airworkflowdemo/model_asset_hierarchy.py
airworkflowdemo/post_commit.py
airworkflowdemo/pre_commit.py
airworkflowdemo/run.py
airworkflowdemo/test.py
airworkflowdemo/model/__init__.py
airworkflowdemo/model/config.py
airworkflowdemo/model/deployment.py
airworkflowdemo/model/project.py
airworkflowdemo/model/schedule.py
airworkflowdemo/model/schedule_assets.py
airworkflowdemo/model/scheduling.py
airworkflowdemo/schemas/config-schema.yaml
airworkflowdemo/util/__init__.py
airworkflowdemo/util/cdf.py
airworkflowdemo/util/convert_string_times.py
airworkflowdemo/util/cron.py
airworkflowdemo/util/env.py
airworkflowdemo/util/file.py
airworkflowdemo/util/functions.py
airworkflowdemo/util/github.py
airworkflowdemo/util/yaml.py
airworkflowdemo-0.0.2.5.dist-info/METADATA
airworkflowdemo-0.0.2.5.dist-info/WHEEL
airworkflowdemo-0.0.2.5.dist-info/top_level.txt
airworkflowdemo-0.0.2.5.dist-info/RECORD
