Metadata-Version: 2.1
Name: airworkflowdemo
Version: 0.0.2.5
Summary: A small example package to test backend functionality
Home-page: https://github.com/mcarun123/air_backend_test
Author: Zana
Author-email: aarunkaashyap@gmail.com
License: UNKNOWN
Platform: UNKNOWN
Classifier: Programming Language :: Python :: 3
Classifier: License :: OSI Approved :: MIT License
Classifier: Operating System :: OS Independent
Requires-Python: >=3.6
Requires-Dist: cognite-sdk (==2.4.1)
Requires-Dist: cognite-sdk-experimental (==0.20.1)
Requires-Dist: PyGithub (==1.53)
Requires-Dist: gitdb (==4.0.5)
Requires-Dist: gitpython (==3.1.8)
Requires-Dist: pytest (==5.4.3)
